pyu/__init__.py
pyu-0.0.1.dist-info/DESCRIPTION.rst
pyu-0.0.1.dist-info/METADATA
pyu-0.0.1.dist-info/RECORD
pyu-0.0.1.dist-info/WHEEL
pyu-0.0.1.dist-info/metadata.json
pyu-0.0.1.dist-info/top_level.txt
util/__init__.py
