Metadata-Version: 2.0
Name: pyu
Version: 0.0.1
Summary: pyu, python utilities, util.
Home-page: https://github.com/jks-liu/util.py
Author: Meme Kagurazaka
Author-email: github@mrliu.org
License: Public Domain
Keywords: pyu util utilities
Platform: UNKNOWN
Classifier: Development Status :: 5 - Production/Stable
Classifier: Intended Audience :: Developers
Classifier: Topic :: Software Development :: Libraries
Classifier: License :: Public Domain
Classifier: Programming Language :: Python :: 2
Classifier: Programming Language :: Python :: 2.7
Classifier: Programming Language :: Python :: 3
Classifier: Programming Language :: Python :: 3.5
Classifier: Programming Language :: Python :: 3.6
Requires-Dist: decorator
